autobuild/.git-credentials
autobuild/.gitconfig
autobuild/__init__.py
autobuild/autobuild.py
autobuild/config.ini
autobuild/readme.txt
autobuild/run.bat
auto_build-1.0.0.dist-info/METADATA
auto_build-1.0.0.dist-info/WHEEL
auto_build-1.0.0.dist-info/top_level.txt
auto_build-1.0.0.dist-info/zip-safe
auto_build-1.0.0.dist-info/RECORD
